zipcodes/__init__.py
zipcodes/zips.json.bz2
zipcodes/__pycache__/__init__.cpython-37.pyc
zipcodes/__pycache__/__init__.cpython-39.pyc
zipcodes-1.1.3.dist-info/LICENSE.txt
zipcodes-1.1.3.dist-info/METADATA
zipcodes-1.1.3.dist-info/WHEEL
zipcodes-1.1.3.dist-info/top_level.txt
zipcodes-1.1.3.dist-info/RECORD
