Metadata-Version: 2.1
Name: zipcodes
Version: 1.1.3
Summary: Query U.S. state zipcodes without SQLite.
Home-page: https://github.com/seanpianka/zipcodes
Author: Sean Pianka
Author-email: pianka@eml.cc
License: MIT
Keywords: zipcode zip code us state query filter validate sqlite
Platform: UNKNOWN
Classifier: Development Status :: 5 - Production/Stable
Classifier: Intended Audience :: Developers
Classifier: Topic :: Software Development :: Build Tools
Classifier: License :: OSI Approved :: MIT License
Classifier: Programming Language :: Python :: 2.6
Classifier: Programming Language :: Python :: 2.7
Classifier: Programming Language :: Python :: 3.5
Classifier: Programming Language :: Python :: 3.6
Classifier: Programming Language :: Python :: 3.7
Classifier: Programming Language :: Python :: 3.8
Classifier: Programming Language :: Python :: 3.9
License-File: LICENSE.txt
